soigia/__init__.py
soigia/admin.py
soigia/apps.py
soigia/contants.py
soigia/env.py
soigia/main.py
soigia/models.py
soigia/abc/__init__.py
soigia/abc/strategy.py
soigia/apis/__init__.py
soigia/apis/markets.py
soigia/auth/__init__.py
soigia/db/__init__.py
soigia/decorators/__init__.py
soigia/exceptions/__init__.py
soigia/helpers/__init__.py
soigia/migrations/0001_initial.py
soigia/migrations/__init__.py
soigia/mixins/__init__.py
soigia/mixins/models.py
soigia/services/__init__.py
soigia/tests/__init__.py
soigia/tests/tests.py
soigia/tools/__init__.py
soigia-0.1.1.dist-info/METADATA
soigia-0.1.1.dist-info/WHEEL
soigia-0.1.1.dist-info/top_level.txt
soigia-0.1.1.dist-info/RECORD
